xeus_python_shell/__init__.py
xeus_python_shell/compiler.py
xeus_python_shell/debugger.py
xeus_python_shell/display.py
xeus_python_shell/shell.py
xeus_python_shell-0.6.6.dist-info/licenses/LICENSE
xeus_python_shell-0.6.6.dist-info/METADATA
xeus_python_shell-0.6.6.dist-info/WHEEL
xeus_python_shell-0.6.6.dist-info/top_level.txt
xeus_python_shell-0.6.6.dist-info/RECORD
