Metadata-Version: 2.4
Name: xeus-python-shell
Version: 0.6.6
Summary: The xeus-python core python logic.
Home-page: https://github.com/jupyter-xeus/xeus-python-shell
Author: QuantStack dev team
Maintainer: QuantStack dev team
License: BSD 3-Clause
Keywords: python ipython xeus-python
Platform: any
Classifier: Intended Audience :: Developers
Classifier: Operating System :: OS Independent
Classifier: Programming Language :: Python :: 3
Classifier: Programming Language :: Python :: 3.6
Classifier: Programming Language :: Python :: 3.7
Classifier: Programming Language :: Python :: 3.8
Classifier: Programming Language :: Python :: 3.9
Classifier: Programming Language :: Python :: 3.10
Classifier: Programming Language :: Python :: 3.11
Classifier: Programming Language :: Python :: 3.12
Classifier: Programming Language :: Python :: 3.13
Classifier: Programming Language :: Python :: 3.14
Classifier: Topic :: Software Development :: Libraries :: Python Modules
Requires-Python: >=3.6
License-File: LICENSE
Requires-Dist: debugpy<2,>=1.1.0
Provides-Extra: ipython
Requires-Dist: ipython>=7.21; extra == "ipython"
Provides-Extra: wasm
Requires-Dist: pyjs<2.0.0,>=1.1.0; extra == "wasm"
Requires-Dist: packaging; extra == "wasm"
Requires-Dist: pyodide-http; extra == "wasm"
Dynamic: author
Dynamic: classifier
Dynamic: home-page
Dynamic: keywords
Dynamic: license
Dynamic: license-file
Dynamic: maintainer
Dynamic: platform
Dynamic: provides-extra
Dynamic: requires-dist
Dynamic: requires-python
Dynamic: summary
